odoo/addons/web_systray_button_init_action/README.rst
odoo/addons/web_systray_button_init_action/__init__.py
odoo/addons/web_systray_button_init_action/__manifest__.py
odoo/addons/web_systray_button_init_action/i18n/it.po
odoo/addons/web_systray_button_init_action/i18n/web_systray_button_init_action.pot
odoo/addons/web_systray_button_init_action/readme/CONFIGURE.md
odoo/addons/web_systray_button_init_action/readme/CONTRIBUTORS.md
odoo/addons/web_systray_button_init_action/readme/DESCRIPTION.md
odoo/addons/web_systray_button_init_action/static/description/icon.png
odoo/addons/web_systray_button_init_action/static/description/index.html
odoo/addons/web_systray_button_init_action/static/src/button/button.esm.js
odoo/addons/web_systray_button_init_action/static/src/button/button.scss
odoo/addons/web_systray_button_init_action/static/src/button/button.xml
odoo/addons/web_systray_button_init_action/static/src/tours/tour.esm.js
odoo/addons/web_systray_button_init_action/tests/__init__.py
odoo/addons/web_systray_button_init_action/tests/test_web_systray_button_init_action.py
odoo_addon_web_systray_button_init_action-18.0.1.0.2.dist-info/METADATA
odoo_addon_web_systray_button_init_action-18.0.1.0.2.dist-info/WHEEL
odoo_addon_web_systray_button_init_action-18.0.1.0.2.dist-info/top_level.txt
odoo_addon_web_systray_button_init_action-18.0.1.0.2.dist-info/RECORD
